LICENSE
MANIFEST.in
NEWS.rst
README.rst
requirements-test.txt
requirements.txt
setup.py
docs/Makefile
docs/api.rst
docs/browser.rst
docs/bugzilla.rst
docs/command.rst
docs/conf.py
docs/develop.rst
docs/examples.rst
docs/index.rst
docs/install.rst
docs/make.bat
docs/presence.rst
docs/srinfo.rst
docs/swamp.rst
docs/userinfo.rst
python_suseapi.egg-info/PKG-INFO
python_suseapi.egg-info/SOURCES.txt
python_suseapi.egg-info/dependency_links.txt
python_suseapi.egg-info/entry_points.txt
python_suseapi.egg-info/requires.txt
python_suseapi.egg-info/top_level.txt
suseapi/__init__.py
suseapi/browser.py
suseapi/bugzilla.py
suseapi/cacher.py
suseapi/django_test_settings.py
suseapi/main.py
suseapi/maintained.py
suseapi/presence.py
suseapi/products.py
suseapi/srinfo.py
suseapi/swamp.py
suseapi/test_browser.py
suseapi/test_bugzilla.py
suseapi/test_cacher.py
suseapi/test_main.py
suseapi/test_maintained.py
suseapi/test_presence.py
suseapi/test_products.py
suseapi/test_srinfo.py
suseapi/test_userinfo.py
suseapi/userinfo.py
suseapi/testdata/bug-20000000.xml
suseapi/testdata/bug-582198.xml
suseapi/testdata/bug-81871.xml
suseapi/testdata/bug-81872.xml
suseapi/testdata/bug-81873.xml
suseapi/testdata/bug-list.xml
suseapi/testdata/bug-none.xml
suseapi/testdata/maintained/.svn-entries
suseapi/testdata/maintained/_svn
suseapi/testdata/maintained/opensuse
suseapi/testdata/maintained/sles