Metadata-Version: 1.1
Name: python-suseapi
Version: 0.22
Summary: Python module for SUSE APIs.
Home-page: https://github.com/openSUSE/python-suseapi
Author: Michal Čihař
Author-email: mcihar@suse.cz
License: GPLv3+
Download-URL: https://pypi.python.org/pypi/python-suseapi
Keywords: suse,django
Platform: any
Classifier: Development Status :: 4 - Beta
Classifier: Topic :: Internet
Classifier: License :: OSI Approved :: GNU General Public License (GPL)
Classifier: Operating System :: OS Independent
Classifier: Intended Audience :: Developers
Classifier: Programming Language :: Python
Classifier: Programming Language :: Python :: 2.6
Classifier: Programming Language :: Python :: 2.7
